[
  {
    "id": 1,
    "header": "Dhaka Marathon 2024",
    "img": "https://i.ibb.co.com/dmqfnD9/istockphoto-892658004-612x612.jpg",
    "title": "Dhaka Marathon 2024: Race to the Finish Line",
    "registration_date": "2025-01-01",
    "registration_end_date": "2025-02-20",
    "time": "06:00 AM",
    "category": "Full Marathon, Half Marathon, 10K",
    "location": "Dhaka, Bangladesh"
  },
  {
    "id": 2,
    "header": "Chittagong City Run",
    "img": "https://i.ibb.co.com/WKhrvMW/healthy-lifestyle-running-outdoors-23-2151847301.jpg",
    "title": "Chittagong City Run: Race for a Cause",
    "registration_date": "2025-02-15",
    "registration_end_date": "2025-03-10",
    "time": "07:30 AM",
    "category": "5K, 10K, Full Marathon",
    "location": "Chittagong, Bangladesh"
  },
  {
    "id": 3,
    "header": "Sylhet International Marathon",
    "img": "https://i.ibb.co.com/R7jD6vg/healthy-lifestyle-running-outdoors-23-2151847285.jpg",
    "title": "Sylhet International Marathon 2024",
    "registration_date": "2025-03-10",
    "registration_end_date": "2025-04-01",
    "time": "05:30 AM",
    "category": "Full Marathon, Half Marathon",
    "location": "Sylhet, Bangladesh"
  },
  {
    "id": 4,
    "header": "Khulna Coastal Marathon",
    "img": "https://i.ibb.co.com/C2zpv5L/istockphoto-1093869886-612x612.jpg",
    "title": "Khulna Coastal Marathon 2024",
    "registration_date": "2025-04-05",
    "registration_end_date": "2025-04-25",
    "time": "06:45 AM",
    "category": "Full Marathon, 10K",
    "location": "Khulna, Bangladesh"
  },
  {
    "id": 5,
    "header": "Rajshahi Green Marathon",
    "img": "https://i.ibb.co.com/0QvJX6L/istockphoto-1322462186-612x612.jpg",
    "title": "Rajshahi Green Marathon 2024",
    "registration_date": "2025-05-20",
    "registration_end_date": "2025-06-05",
    "time": "06:30 AM",
    "category": "Half Marathon, 5K",
    "location": "Rajshahi, Bangladesh"
  },
  {
    "id": 6,
    "header": "Barisal Sunshine Marathon",
    "img": "https://i.ibb.co.com/fr9kd9q/istockphoto-1404350255-612x612.jpg",
    "title": "Barisal Sunshine Marathon 2024",
    "registration_date": "2025-06-01",
    "registration_end_date": "2025-06-15",
    "time": "07:00 AM",
    "category": "Full Marathon, 5K",
    "location": "Barisal, Bangladesh"
  }
]
